__init__.py
python_selenium_ctrl_package/__init__.py
python_selenium_ctrl_package/conftest_base.py
python_selenium_ctrl_package/main.py
python_selenium_ctrl_package/conf/__init__.py
python_selenium_ctrl_package/conf/product_list.py
python_selenium_ctrl_package/conf/app/__init__.py
python_selenium_ctrl_package/conf/app/ports_conf.py
python_selenium_ctrl_package/conf/rwd/__init__.py
python_selenium_ctrl_package/conf/rwd/Website/__init__.py
python_selenium_ctrl_package/conf/rwd/Website/base_url_conf.py
python_selenium_ctrl_package/conf/rwd/Website/opera_browser_conf.py
python_selenium_ctrl_package/drivers/__init__.py
python_selenium_ctrl_package/drivers/driverfactory.py
python_selenium_ctrl_package/drivers/browsers/__init__.py
python_selenium_ctrl_package/drivers/browsers/browser_os_name_conf.py
python_selenium_ctrl_package/drivers/browsers/local_browsers.py
python_selenium_ctrl_package/drivers/browsers/remote_options.py
python_selenium_ctrl_package/pages/Base_Page.py
python_selenium_ctrl_package/pages/Mobile_Base_Page.py
python_selenium_ctrl_package/pages/__init__.py
python_selenium_ctrl_package/pages/mobile_zero_page.py
python_selenium_ctrl_package/pages/zero_page.py
python_selenium_ctrl_package/remoteTest/BrowserStack_Library.py
python_selenium_ctrl_package/remoteTest/__init__.py
python_selenium_ctrl_package/utils/__init__.py
python_selenium_ctrl_package/utils/email_conf.py
python_selenium_ctrl_package/utils/html_report_conf.py
python_selenium_ctrl_package/utils/remote_credentials.py
python_selenium_ctrl_package/utils/screenshot_conf.py
python_selenium_ctrl_package/utils/general/Base_Logging.py
python_selenium_ctrl_package/utils/general/Credential_Related.py
python_selenium_ctrl_package/utils/general/Gif_Maker.py
python_selenium_ctrl_package/utils/general/Wrapit.py
python_selenium_ctrl_package/utils/general/__init__.py
python_selenium_ctrl_package/utils/general/email_pytest_report.py
python_selenium_ctrl_package/utils/general/stop_test_exception_util.py
python_selenium_ctrl_package-0.0.237.dist-info/LICENSE
python_selenium_ctrl_package-0.0.237.dist-info/METADATA
python_selenium_ctrl_package-0.0.237.dist-info/WHEEL
python_selenium_ctrl_package-0.0.237.dist-info/top_level.txt
python_selenium_ctrl_package-0.0.237.dist-info/RECORD
