Metadata-Version: 2.1
Name: python_selenium_ctrl_package
Version: 0.0.237
Summary: Base_page for selenium automation
Author-email: "QHMS(App team)" <qhmsqaexpert@gmail.com>
Classifier: Programming Language :: Python :: 3
Classifier: License :: OSI Approved :: MIT License
Classifier: Operating System :: OS Independent
Requires-Python: >=3.7
License-File: LICENSE
Requires-Dist: requests ==2.25.1
Requires-Dist: reportportal-client ==5.2.5
Requires-Dist: pytest ==7.4.4
Requires-Dist: selenium ==4.17.2
Requires-Dist: python-dotenv ==0.16.0
Requires-Dist: Appium-Python-Client ==3.1.1
Requires-Dist: pytest-xdist >=1.31
Requires-Dist: pytest-html >=3.2.0
Requires-Dist: pytest-rerunfailures >=9.1.1
Requires-Dist: pytest-reportportal ==5.0.10
Requires-Dist: pillow >=9.3.0
Requires-Dist: tesults
Requires-Dist: loguru ==0.6.0
Requires-Dist: imageio ~=2.9.0
Requires-Dist: questionary >=1.9.0
Requires-Dist: clear-screen >=0.1.14
Requires-Dist: prompt-toolkit ==2.0.10
Requires-Dist: openpyxl ==3.1.2
Requires-Dist: pytest-bdd ~=6.1.1
Requires-Dist: pandas ~=2.0.0
Requires-Dist: numpy ~=1.26.0
Requires-Dist: PyHamcrest
Requires-Dist: webdriver-manager
Requires-Dist: python-selenium-ctrl-package
